[
  {
    "id": 1,
    "card": [
      [15, 22, 37, 56, 65],
      [2, 27, 41, 52, 68],
      [7, 17, 0, 57, 67],
      [14, 18, 36, 59, 73],
      [11, 24, 38, 58, 63]
    ]
  },
  {
    "id": 2,
    "card": [
      [11, 26, 43, 59, 75],
      [12, 22, 39, 51, 62],
      [6, 18, 0, 56, 65],
      [13, 28, 33, 52, 66],
      [8, 23, 40, 47, 71]
    ]
  },
  {
    "id": 3,
    "card": [
      [13, 17, 44, 55, 75],
      [5, 18, 35, 50, 64],
      [6, 16, 0, 54, 68],
      [9, 27, 45, 51, 70],
      [10, 19, 34, 57, 61]
    ]
  },
  {
    "id": 4,
    "card": [
      [6, 20, 38, 51, 66],
      [13, 25, 43, 56, 69],
      [7, 23, 0, 48, 74],
      [3, 16, 32, 47, 68],
      [12, 19, 31, 52, 62]
    ]
  },
  {
    "id": 5,
    "card": [
      [14, 30, 31, 57, 61],
      [2, 29, 41, 60, 62],
      [11, 17, 0, 54, 66],
      [15, 25, 38, 46, 63],
      [6, 20, 37, 52, 74]
    ]
  },
  {
    "id": 6,
    "card": [
      [15, 18, 39, 47, 73],
      [10, 29, 42, 48, 61],
      [6, 27, 0, 54, 72],
      [9, 25, 36, 49, 63],
      [7, 23, 44, 57, 67]
    ]
  },
  {
    "id": 7,
    "card": [
      [1, 20, 37, 55, 54],
      [2, 21, 34, 49, 66],
      [3, 28, 0, 56, 63],
      [5, 24, 41, 59, 65],
      [8, 16, 44, 47, 67]
    ]
  },
  {
    "id": 8,
    "card": [
      [2, 24, 40, 50, 62],
      [6, 21, 43, 60, 63],
      [11, 19, 0, 58, 64],
      [15, 27, 34, 47, 69],
      [1, 28, 35, 51, 73]
    ]
  },
  {
    "id": 9,
    "card": [
      [5, 20, 35, 53, 73],
      [7, 28, 43, 59, 74],
      [1, 17, 0, 56, 66],
      [9, 27, 32, 51, 70],
      [15, 26, 31, 60, 69]
    ]
  },
  {
    "id": 10,
    "card": [
      [2, 20, 41, 48, 75],
      [6, 29, 39, 46, 68],
      [7, 27, 0, 55, 63],
      [10, 21, 36, 60, 61],
      [1, 25, 37, 49, 67]
    ]
  },
  {
    "id": 11,
    "card": [
      [5, 20, 31, 51, 61],
      [8, 16, 33, 56, 62],
      [15, 26, 0, 54, 71],
      [14, 17, 37, 55, 75],
      [1, 23, 36, 50, 64]
    ]
  },
  {
    "id": 12,
    "card": [
      [15, 23, 41, 60, 63],
      [13, 18, 31, 52, 72],
      [6, 28, 0, 54, 67],
      [7, 24, 39, 49, 68],
      [1, 30, 33, 53, 70]
    ]
  },
  {
    "id": 13,
    "card": [
      [7, 27, 41, 48, 70],
      [15, 28, 43, 60, 72],
      [3, 19, 0, 59, 68],
      [6, 18, 31, 49, 64],
      [5, 30, 33, 46, 66]
    ]
  },
  {
    "id": 14,
    "card": [
      [5, 19, 37, 53, 64],
      [3, 28, 32, 54, 65],
      [11, 18, 0, 57, 63],
      [4, 29, 36, 50, 70],
      [8, 26, 35, 55, 67]
    ]
  },
  {
    "id": 15,
    "card": [
      [5, 26, 43, 59, 66],
      [2, 30, 34, 52, 70],
      [6, 24, 0, 56, 62],
      [11, 20, 35, 49, 65],
      [3, 19, 39, 47, 74]
    ]
  },
  {
    "id": 16,
    "card": [
      [5, 20, 32, 50, 61],
      [12, 19, 40, 55, 75],
      [9, 17, 0, 60, 72],
      [7, 29, 45, 47, 66],
      [6, 16, 41, 49, 63]
    ]
  },
  {
    "id": 17,
    "card": [
      [7, 25, 36, 49, 67],
      [6, 21, 40, 57, 61],
      [11, 16, 0, 51, 66],
      [9, 18, 44, 52, 70],
      [5, 23, 35, 59, 63]
    ]
  },
  {
    "id": 18,
    "card": [
      [11, 28, 39, 58, 70],
      [1, 27, 41, 53, 68],
      [15, 25, 0, 49, 67],
      [3, 26, 43, 52, 63],
      [9, 23, 34, 50, 75]
    ]
  },
  {
    "id": 19,
    "card": [
      [13, 29, 44, 53, 73],
      [4, 24, 41, 48, 62],
      [8, 30, 0, 49, 66],
      [9, 21, 40, 52, 68],
      [10, 16, 39, 55, 65]
    ]
  },
  {
    "id": 20,
    "card": [
      [10, 24, 40, 59, 65],
      [4, 20, 44, 47, 75],
      [15, 23, 0, 50, 67],
      [6, 18, 39, 54, 70],
      [13, 16, 35, 48, 68]
    ]
  },
  {
    "id": 21,
    "card": [
      [14, 29, 37, 51, 66],
      [11, 23, 40, 57, 65],
      [1, 18, 0, 52, 75],
      [2, 22, 36, 47, 74],
      [5, 26, 39, 56, 62]
    ]
  },
  {
    "id": 22,
    "card": [
      [12, 18, 44, 49, 64],
      [7, 25, 40, 56, 71],
      [11, 23, 0, 50, 62],
      [9, 19, 35, 55, 69],
      [8, 22, 37, 51, 73]
    ]
  },
  {
    "id": 23,
    "card": [
      [12, 27, 44, 49, 64],
      [7, 25, 40, 56, 71],
      [2, 20, 0, 50, 62],
      [6, 28, 42, 58, 75],
      [11, 23, 33, 59, 69]
    ]
  },
  {
    "id": 24,
    "card": [
      [9, 24, 40, 54, 69],
      [6, 26, 39, 60, 63],
      [2, 29, 0, 56, 74],
      [12, 23, 35, 48, 72],
      [15, 21, 45, 52, 65]
    ]
  },
  {
    "id": 25,
    "card": [
      [13, 28, 44, 58, 73],
      [10, 30, 43, 49, 67],
      [6, 18, 0, 60, 63],
      [1, 27, 39, 52, 61],
      [4, 25, 34, 56, 69]
    ]
  },
  {
    "id": 26,
    "card": [
      [12, 27, 41, 50, 65],
      [4, 29, 34, 51, 69],
      [11, 26, 0, 46, 71],
      [3, 24, 33, 60, 70],
      [1, 21, 31, 58, 63]
    ]
  },
  {
    "id": 27,
    "card": [
      [9, 26, 45, 47, 74],
      [13, 18, 31, 51, 68],
      [6, 27, 0, 59, 63],
      [11, 16, 42, 60, 69],
      [5, 29, 35, 46, 73]
    ]
  },
  {
    "id": 28,
    "card": [
      [7, 25, 42, 55, 74],
      [13, 28, 43, 46, 67],
      [3, 29, 0, 59, 70],
      [14, 16, 33, 60, 68],
      [6, 20, 34, 50, 72]
    ]
  },
  {
    "id": 29,
    "card": [
      [4, 29, 44, 50, 61],
      [8, 28, 37, 51, 66],
      [1, 17, 0, 52, 68],
      [7, 22, 42, 57, 70],
      [10, 23, 35, 53, 71]
    ]
  },
  {
    "id": 30,
    "card": [
      [3, 27, 39, 56, 65],
      [15, 28, 33, 53, 75],
      [12, 16, 0, 58, 62],
      [13, 26, 32, 54, 71],
      [6, 20, 41, 51, 61]
    ]
  },
  {
    "id": 31,
    "card": [
      [5, 16, 35, 49, 70],
      [9, 23, 42, 60, 67],
      [4, 26, 0, 56, 73],
      [3, 20, 45, 50, 61],
      [6, 25, 44, 54, 74]
    ]
  },
  {
    "id": 32,
    "card": [
      [7, 24, 44, 58, 69],
      [14, 16, 42, 60, 72],
      [8, 29, 0, 46, 74],
      [1, 21, 34, 59, 62],
      [9, 17, 33, 49, 75]
    ]
  },
  {
    "id": 33,
    "card": [
      [14, 26, 33, 47, 69],
      [7, 18, 44, 55, 67],
      [12, 25, 0, 52, 65],
      [9, 20, 45, 56, 73],
      [13, 19, 42, 51, 62]
    ]
  },
  {
    "id": 34,
    "card": [
      [11, 16, 33, 56, 74],
      [3, 17, 38, 58, 73],
      [15, 27, 0, 50, 67],
      [13, 25, 36, 57, 66],
      [2, 24, 32, 52, 65]
    ]
  },
  {
    "id": 35,
    "card": [
      [8, 20, 35, 50, 70],
      [1, 23, 38, 53, 73],
      [11, 19, 0, 51, 68],
      [3, 28, 43, 56, 67],
      [5, 27, 41, 59, 63]
    ]
  },
  {
    "id": 36,
    "card": [
      [15, 20, 42, 51, 70],
      [3, 18, 44, 47, 67],
      [4, 28, 0, 60, 74],
      [8, 24, 39, 49, 73],
      [13, 22, 31, 56, 75]
    ]
  },
  {
    "id": 37,
    "card": [
      [12, 27, 44, 55, 69],
      [1, 22, 37, 51, 63],
      [4, 24, 0, 57, 64],
      [8, 21, 43, 53, 71],
      [6, 20, 41, 54, 70]
    ]
  },
  {
    "id": 38,
    "card": [
      [10, 21, 32, 49, 74],
      [1, 18, 41, 48, 75],
      [2, 19, 0, 60, 62],
      [6, 27, 37, 53, 67],
      [8, 29, 35, 55, 68]
    ]
  },
  {
    "id": 39,
    "card": [
      [14, 23, 45, 60, 63],
      [5, 28, 38, 52, 72],
      [7, 30, 0, 59, 62],
      [2, 22, 32, 54, 67],
      [9, 19, 31, 56, 70]
    ]
  },
  {
    "id": 40,
    "card": [
      [1, 29, 36, 52, 66],
      [4, 23, 33, 47, 73],
      [9, 30, 0, 60, 63],
      [3, 20, 45, 55, 69],
      [6, 24, 42, 46, 74]
    ]
  },
  {
    "id": 41,
    "card": [
      [1, 23, 31, 60, 69],
      [6, 22, 37, 50, 70],
      [13, 19, 0, 58, 75],
      [5, 28, 42, 54, 64],
      [3, 27, 38, 47, 66]
    ]
  },
  {
    "id": 42,
    "card": [
      [15, 16, 45, 60, 67],
      [1, 22, 41, 54, 70],
      [4, 30, 0, 56, 62],
      [5, 26, 44, 51, 75],
      [8, 25, 31, 48, 71]
    ]
  },
  {
    "id": 43,
    "card": [
      [11, 17, 35, 48, 62],
      [5, 23, 38, 52, 75],
      [7, 25, 0, 51, 63],
      [1, 26, 44, 53, 73],
      [15, 30, 41, 46, 65]
    ]
  },
  {
    "id": 44,
    "card": [
      [12, 19, 44, 46, 61],
      [8, 16, 42, 48, 71],
      [7, 26, 0, 56, 67],
      [1, 17, 45, 58, 64],
      [5, 29, 38, 54, 74]
    ]
  },
  {
    "id": 45,
    "card": [
      [2, 26, 36, 60, 67],
      [5, 19, 45, 56, 66],
      [7, 22, 0, 47, 69],
      [6, 28, 38, 55, 63],
      [4, 27, 37, 57, 62]
    ]
  },
  {
    "id": 46,
    "card": [
      [8, 19, 45, 57, 69],
      [10, 24, 35, 49, 62],
      [9, 30, 0, 53, 66],
      [11, 18, 44, 51, 65],
      [4, 25, 31, 48, 68]
    ]
  },
  {
    "id": 47,
    "card": [
      [14, 29, 38, 53, 66],
      [11, 20, 35, 58, 74],
      [10, 17, 0, 59, 61],
      [4, 25, 44, 56, 75],
      [7, 23, 37, 49, 64]
    ]
  },
  {
    "id": 48,
    "card": [
      [14, 22, 45, 53, 67],
      [7, 23, 44, 59, 74],
      [8, 29, 0, 52, 68],
      [10, 24, 34, 55, 70],
      [9, 25, 38, 54, 71]
    ]
  },
  {
    "id": 49,
    "card": [
      [1, 24, 35, 59, 64],
      [7, 29, 40, 50, 73],
      [8, 23, 0, 57, 75],
      [12, 27, 32, 48, 61],
      [10, 18, 39, 54, 62]
    ]
  },
  {
    "id": 50,
    "card": [
      [13, 27, 32, 57, 74],
      [15, 17, 31, 46, 65],
      [8, 30, 0, 55, 63],
      [3, 21, 34, 60, 70],
      [5, 25, 37, 53, 66]
    ]
  },
  {
    "id": 51,
    "card": [
      [15, 16, 43, 56, 63],
      [14, 30, 32, 49, 65],
      [9, 20, 0, 51, 62],
      [11, 25, 44, 52, 69],
      [4, 26, 34, 48, 70]
    ]
  },
  {
    "id": 52,
    "card": [
      [2, 21, 35, 59, 68],
      [3, 19, 41, 58, 67],
      [11, 24, 0, 54, 62],
      [5, 16, 34, 53, 65],
      [7, 17, 39, 47, 63]
    ]
  },
  {
    "id": 53,
    "card": [
      [9, 28, 40, 51, 71],
      [1, 29, 31, 46, 75],
      [2, 27, 0, 50, 64],
      [5, 23, 41, 47, 66],
      [6, 30, 45, 53, 72]
    ]
  },
  {
    "id": 54,
    "card": [
      [13, 20, 34, 47, 63],
      [2, 21, 44, 58, 73],
      [3, 28, 0, 48, 62],
      [6, 16, 43, 50, 66],
      [5, 17, 38, 51, 65]
    ]
  },
  {
    "id": 55,
    "card": [
      [14, 16, 45, 56, 75],
      [8, 23, 43, 47, 69],
      [1, 19, 0, 57, 74],
      [5, 18, 41, 52, 72],
      [11, 21, 34, 46, 68]
    ]
  },
  {
    "id": 56,
    "card": [
      [1, 25, 36, 60, 74],
      [5, 30, 43, 50, 72],
      [7, 21, 0, 55, 69],
      [12, 24, 34, 51, 71],
      [15, 17, 40, 49, 63]
    ]
  },
  {
    "id": 57,
    "card": [
      [10, 23, 33, 60, 69],
      [2, 20, 40, 56, 75],
      [3, 22, 0, 59, 68],
      [7, 30, 44, 53, 65],
      [9, 19, 31, 58, 61]
    ]
  },
  {
    "id": 58,
    "card": [
      [2, 30, 32, 46, 62],
      [5, 21, 35, 51, 63],
      [13, 20, 0, 50, 64],
      [11, 23, 39, 54, 66],
      [1, 29, 44, 57, 73]
    ]
  },
  {
    "id": 59,
    "card": [
      [13, 19, 39, 52, 71],
      [1, 25, 37, 50, 74],
      [4, 18, 0, 55, 61],
      [7, 21, 44, 47, 64],
      [5, 30, 41, 49, 66]
    ]
  },
  {
    "id": 60,
    "card": [
      [4, 22, 36, 49, 61],
      [2, 18, 37, 60, 63],
      [14, 26, 0, 59, 65],
      [7, 21, 42, 57, 73],
      [10, 20, 31, 46, 75]
    ]
  },
  {
    "id": 61,
    "card": [
      [12, 25, 37, 57, 69],
      [8, 23, 43, 53, 65],
      [6, 18, 0, 46, 72],
      [1, 16, 44, 48, 62],
      [9, 24, 32, 56, 68]
    ]
  },
  {
    "id": 62,
    "card": [
      [1, 20, 31, 54, 69],
      [7, 28, 36, 60, 68],
      [15, 30, 0, 47, 74],
      [11, 17, 37, 53, 67],
      [3, 22, 44, 58, 72]
    ]
  },
  {
    "id": 63,
    "card": [
      [3, 17, 40, 46, 73],
      [13, 21, 42, 52, 63],
      [6, 20, 0, 56, 69],
      [9, 19, 34, 47, 71],
      [10, 26, 45, 53, 68]
    ]
  },
  {
    "id": 64,
    "card": [
      [12, 19, 38, 50, 66],
      [3, 21, 34, 52, 71],
      [4, 22, 0, 48, 72],
      [6, 26, 33, 58, 62],
      [9, 20, 42, 57, 64]
    ]
  },
  {
    "id": 65,
    "card": [
      [13, 16, 31, 58, 75],
      [5, 25, 37, 60, 62],
      [8, 26, 0, 47, 64],
      [9, 27, 43, 49, 66],
      [11, 22, 44, 51, 68]
    ]
  },
  {
    "id": 66,
    "card": [
      [11, 25, 37, 59, 72],
      [7, 27, 40, 47, 67],
      [1, 23, 0, 52, 69],
      [10, 24, 45, 49, 66],
      [4, 16, 39, 60, 63]
    ]
  },
  {
    "id": 67,
    "card": [
      [12, 27, 42, 47, 61],
      [13, 26, 39, 54, 72],
      [6, 21, 0, 50, 74],
      [5, 24, 33, 58, 69],
      [11, 23, 36, 56, 70]
    ]
  },
  {
    "id": 68,
    "card": [
      [7, 30, 35, 59, 62],
      [15, 29, 33, 60, 67],
      [11, 27, 0, 51, 71],
      [4, 26, 37, 52, 73],
      [13, 22, 31, 55, 66]
    ]
  },
  {
    "id": 69,
    "card": [
      [15, 18, 34, 49, 68],
      [5, 20, 40, 51, 61],
      [7, 22, 0, 56, 69],
      [6, 26, 35, 58, 62],
      [9, 28, 42, 52, 70]
    ]
  },
  {
    "id": 70,
    "card": [
      [7, 29, 43, 58, 68],
      [8, 23, 33, 47, 67],
      [10, 24, 0, 48, 69],
      [12, 17, 39, 52, 73],
      [14, 18, 36, 56, 62]
    ]
  },
  {
    "id": 71,
    "card": [
      [2, 30, 31, 47, 73],
      [3, 16, 36, 53, 71],
      [8, 26, 0, 56, 68],
      [6, 23, 33, 58, 75],
      [9, 19, 45, 50, 63]
    ]
  },
  {
    "id": 72,
    "card": [
      [2, 23, 42, 56, 63],
      [11, 28, 40, 53, 70],
      [8, 21, 0, 57, 64],
      [7, 27, 44, 55, 66],
      [1, 19, 35, 48, 72]
    ]
  },
  {
    "id": 73,
    "card": [
      [14, 18, 37, 60, 62],
      [7, 4, 31, 51, 63],
      [13, 30, 0, 55, 71],
      [10, 25, 43, 58, 74],
      [3, 22, 38, 56, 64]
    ]
  },
  {
    "id": 74,
    "card": [
      [10, 19, 39, 53, 65],
      [6, 23, 35, 47, 72],
      [15, 16, 0, 57, 74],
      [5, 22, 34, 52, 73],
      [7, 17, 44, 60, 61]
    ]
  },
  {
    "id": 75,
    "card": [
      [10, 27, 41, 57, 73],
      [1, 29, 35, 51, 62],
      [3, 17, 0, 54, 64],
      [9, 19, 32, 47, 65],
      [4, 24, 39, 58, 69]
    ]
  },
  {
    "id": 76,
    "card": [
      [14, 30, 31, 47, 62],
      [15, 29, 34, 60, 63],
      [2, 19, 0, 59, 68],
      [5, 21, 39, 54, 70],
      [7, 23, 41, 55, 69]
    ]
  },
  {
    "id": 77,
    "card": [
      [15, 22, 38, 49, 67],
      [11, 23, 37, 52, 72],
      [10, 29, 0, 47, 71],
      [8, 18, 39, 56, 66],
      [9, 20, 36, 60, 63]
    ]
  },
  {
    "id": 78,
    "card": [
      [13, 18, 34, 53, 68],
      [4, 17, 41, 52, 61],
      [3, 20, 0, 59, 64],
      [10, 29, 32, 54, 65],
      [5, 28, 40, 50, 73]
    ]
  },
  {
    "id": 79,
    "card": [
      [3, 26, 39, 46, 71],
      [2, 30, 42, 57, 61],
      [12, 19, 0, 58, 66],
      [4, 22, 38, 59, 67],
      [6, 21, 40, 52, 62]
    ]
  },
  {
    "id": 80,
    "card": [
      [2, 23, 45, 53, 70],
      [12, 18, 36, 58, 64],
      [15, 20, 0, 48, 63],
      [7, 22, 34, 52, 71],
      [3, 16, 42, 46, 72]
    ]
  },
  {
    "id": 81,
    "card": [
      [13, 28, 43, 48, 74],
      [9, 19, 37, 57, 68],
      [11, 23, 0, 56, 61],
      [4, 30, 44, 51, 67],
      [6, 16, 38, 46, 75]
    ]
  },
  {
    "id": 82,
    "card": [
      [11, 23, 40, 56, 68],
      [2, 28, 45, 47, 72],
      [7, 27, 0, 59, 73],
      [6, 20, 38, 51, 63],
      [12, 30, 35, 46, 74]
    ]
  },
  {
    "id": 83,
    "card": [
      [5, 26, 45, 56, 70],
      [11, 18, 43, 49, 74],
      [1, 28, 0, 52, 66],
      [4, 21, 41, 57, 68],
      [10, 23, 38, 59, 69]
    ]
  },
  {
    "id": 84,
    "card": [
      [3, 27, 45, 52, 73],
      [7, 18, 44, 55, 67],
      [12, 25, 0, 58, 65],
      [9, 20, 40, 56, 70],
      [13, 19, 42, 51, 62]
    ]
  },
  {
    "id": 85,
    "card": [
      [7, 30, 35, 54, 62],
      [5, 29, 33, 60, 67],
      [11, 27, 0, 51, 71],
      [4, 26, 37, 52, 73],
      [13, 22, 31, 59, 66]
    ]
  },
  {
    "id": 86,
    "card": [
      [7, 22, 38, 56, 74],
      [9, 28, 44, 46, 67],
      [13, 19, 0, 59, 73],
      [15, 16, 36, 57, 61],
      [14, 29, 40, 50, 65]
    ]
  },
  {
    "id": 87,
    "card": [
      [12, 16, 37, 58, 73],
      [1, 20, 40, 48, 75],
      [7, 19, 0, 50, 70],
      [8, 26, 33, 56, 67],
      [6, 4, 38, 54, 63]
    ]
  },
  {
    "id": 88,
    "card": [
      [7, 24, 41, 54, 70],
      [10, 18, 44, 59, 75],
      [15, 17, 0, 58, 73],
      [2, 28, 34, 57, 67],
      [3, 22, 31, 53, 71]
    ]
  },
  {
    "id": 89,
    "card": [
      [7, 18, 38, 50, 69],
      [10, 29, 42, 59, 74],
      [15, 16, 0, 56, 70],
      [1, 24, 43, 49, 73],
      [5, 23, 33, 48, 65]
    ]
  },
  {
    "id": 90,
    "card": [
      [14, 29, 39, 60, 70],
      [13, 28, 42, 47, 71],
      [5, 20, 0, 48, 65],
      [9, 26, 31, 49, 68],
      [8, 17, 15, 59, 72]
    ]
  },
  {
    "id": 91,
    "card": [
      [12, 17, 33, 52, 61],
      [6, 19, 42, 57, 69],
      [8, 21, 0, 60, 75],
      [11, 25, 34, 55, 68],
      [7, 26, 43, 46, 71]
    ]
  },
  {
    "id": 92,
    "card": [
      [6, 23, 39, 56, 75],
      [12, 24, 40, 58, 66],
      [8, 30, 0, 48, 68],
      [7, 20, 42, 49, 62],
      [2, 21, 36, 51, 70]
    ]
  },
  {
    "id": 93,
    "card": [
      [15, 23, 36, 52, 71],
      [14, 30, 41, 59, 68],
      [2, 29, 0, 55, 75],
      [5, 21, 40, 54, 63],
      [4, 20, 37, 58, 70]
    ]
  },
  {
    "id": 94,
    "card": [
      [8, 28, 42, 49, 71],
      [1, 29, 44, 54, 73],
      [4, 20, 0, 60, 63],
      [7, 19, 32, 50, 65],
      [6, 16, 34, 47, 67]
    ]
  },
  {
    "id": 95,
    "card": [
      [15, 24, 37, 46, 63],
      [5, 20, 35, 52, 67],
      [13, 30, 0, 56, 74],
      [2, 23, 40, 47, 75],
      [8, 27, 39, 60, 66]
    ]
  },
  {
    "id": 96,
    "card": [
      [6, 21, 36, 57, 63],
      [14, 25, 45, 46, 61],
      [13, 27, 0, 48, 66],
      [3, 24, 35, 59, 65],
      [5, 29, 43, 54, 62]
    ]
  },
  {
    "id": 97,
    "card": [
      [8, 24, 38, 53, 71],
      [9, 30, 34, 47, 69],
      [12, 23, 0, 49, 70],
      [3, 19, 37, 59, 68],
      [1, 18, 39, 56, 63]
    ]
  },
  {
    "id": 98,
    "card": [
      [8, 16, 37, 57, 68],
      [13, 29, 36, 54, 63],
      [3, 21, 0, 56, 67],
      [6, 26, 33, 52, 70],
      [5, 24, 45, 59, 73]
    ]
  },
  {
    "id": 99,
    "card": [
      [12, 28, 36, 51, 68],
      [10, 21, 45, 50, 74],
      [4, 16, 0, 60, 70],
      [6, 22, 39, 56, 72],
      [1, 27, 40, 49, 63]
    ]
  },
  {
    "id": 100,
    "card": [
      [6, 18, 42, 53, 68],
      [7, 16, 41, 55, 75],
      [1, 19, 0, 48, 74],
      [5, 22, 33, 56, 69],
      [14, 30, 39, 51, 65]
    ]
  }
]